aicsmlsegment/__init__.py
aicsmlsegment/custom_loss.py
aicsmlsegment/custom_metrics.py
aicsmlsegment/model_utils.py
aicsmlsegment/training_utils.py
aicsmlsegment/utils.py
aicsmlsegment/version.py
aicsmlsegment/Net3D/__init__.py
aicsmlsegment/Net3D/uNet_original.py
aicsmlsegment/Net3D/unet_xy.py
aicsmlsegment/Net3D/unet_xy_enlarge.py
aicsmlsegment-0.0.7.dist-info/LICENSE.txt
aicsmlsegment-0.0.7.dist-info/METADATA
aicsmlsegment-0.0.7.dist-info/WHEEL
aicsmlsegment-0.0.7.dist-info/entry_points.txt
aicsmlsegment-0.0.7.dist-info/top_level.txt
aicsmlsegment-0.0.7.dist-info/RECORD
