Metadata-Version: 2.1
Name: aicsmlsegment
Version: 0.0.7
Summary: Scripts for ML structure segmentation.
Home-page: UNKNOWN
Author: AICS
Author-email: jianxuc@alleninstitute.org
License: Allen Institute Software License
Platform: UNKNOWN
Requires-Dist: numpy (>=1.15.1)
Requires-Dist: scipy (>=1.1.0)
Requires-Dist: scikit-image
Requires-Dist: pandas (>=0.23.4)
Requires-Dist: aicsimageio (>3.3.0)
Requires-Dist: tqdm
Requires-Dist: pyyaml
Provides-Extra: all
Requires-Dist: pytest ; extra == 'all'
Requires-Dist: pytest-cov ; extra == 'all'
Requires-Dist: flake8 ; extra == 'all'
Provides-Extra: lint_group
Requires-Dist: flake8 ; extra == 'lint_group'
Provides-Extra: test_group
Requires-Dist: pytest ; extra == 'test_group'
Requires-Dist: pytest-cov ; extra == 'test_group'
